Metadata-Version: 1.0
Name: dsnk-distributions
Version: 0.2
Summary: Gaussian and Binomial distributions
Home-page: UNKNOWN
Author: ASIFIWE Emmanuel
Author-email: emmanuel2koestner@gmail.com
License: UNKNOWN
Platform: UNKNOWN
